{
  "project_info": {
    "project_number": "641633396301",
    "firebase_url": "https://share-idea-89a4c.firebaseio.com",
    "project_id": "share-idea-89a4c",
    "storage_bucket": "share-idea-89a4c.appspot.com"
  },
  "client": [
    {
      "client_info": {
        "mobilesdk_app_id": "1:641633396301:android:309151eb833411a1b91e04",
        "android_client_info": {
          "package_name": "com.example.shareidea"
        }
      },
      "oauth_client": [
        {
          "client_id": "641633396301-3j4rjc2ph09jg6q1i5hoqq6hp19bda3u.apps.googleusercontent.com",
          "client_type": 3
        }
      ],
      "api_key": [
        {
          "current_key": "AIzaSyA6bfU1Am2BczW7tE1ozJSDTp1IiKOAMWQ"
        }
      ],
      "services": {
        "appinvite_service": {
          "other_platform_oauth_client": [
            {
              "client_id": "641633396301-3j4rjc2ph09jg6q1i5hoqq6hp19bda3u.apps.googleusercontent.com",
              "client_type": 3
            }
          ]
        }
      }
    }
  ],
  "configuration_version": "1"
}